api/__init__.py
api/formatters.py
api/validators.py
api/cli/__init__.py
api/cli/__main__.py
api/cli/ingest.py
api/cli/quality.py
api/cli/repl.py
api/cli/search.py
api/use_cases/__init__.py
api/use_cases/ingest.py
api/use_cases/rag.py
api/use_cases/search.py
domain/__init__.py
domain/entities.py
domain/exceptions.py
domain/value_objects.py
embedding/__init__.py
embedding/doc_id.py
embedding/provider.py
embedding/validators.py
generation/__init__.py
generation/client.py
generation/models.py
generation/pipeline.py
generation/prompts.py
ingestion/__init__.py
ingestion/chunking.py
ingestion/concept_builder.py
ingestion/models.py
ingestion/segmentation.py
ingestion/parsers/__init__.py
ingestion/parsers/base.py
ingestion/parsers/markdown.py
ingestion/parsers/ocr.py
ingestion/parsers/pymupdf_parser.py
jw_my_rag-0.1.1.dist-info/licenses/LICENSE
retrieval/__init__.py
retrieval/context.py
retrieval/grouping.py
retrieval/pipeline.py
retrieval/query.py
retrieval/search.py
retrieval/self_query.py
shared/__init__.py
shared/batching.py
shared/config.py
shared/db_pool.py
shared/exceptions.py
shared/hashing.py
shared/text_utils.py
storage/__init__.py
storage/cascade.py
storage/db.py
storage/metrics.py
storage/parent_store.py
storage/schema.py
storage/vector_store.py
storage/adapters/__init__.py
storage/adapters/langchain_adapter.py
storage/repositories/__init__.py
storage/repositories/base.py
storage/repositories/concept_repo.py
storage/repositories/document_repo.py
storage/repositories/embedding_repo.py
storage/repositories/fragment_repo.py
jw_my_rag-0.1.1.dist-info/METADATA
jw_my_rag-0.1.1.dist-info/WHEEL
jw_my_rag-0.1.1.dist-info/entry_points.txt
jw_my_rag-0.1.1.dist-info/top_level.txt
jw_my_rag-0.1.1.dist-info/RECORD
