Metadata-Version: 2.4
Name: jw-my-rag
Version: 0.1.1
Summary: OCR Vector Database - Document parsing, semantic segmentation, and vector search
Author-email: Jaewon <jaewonheo666@gmail.com>
License: MIT
Project-URL: Homepage, https://github.com/ocr-vector-db/ocr-vector-db
Project-URL: Documentation, https://github.com/ocr-vector-db/ocr-vector-db#readme
Project-URL: Repository, https://github.com/ocr-vector-db/ocr-vector-db
Project-URL: Issues, https://github.com/ocr-vector-db/ocr-vector-db/issues
Keywords: ocr,vector-database,embedding,semantic-search,rag,langchain,pgvector,document-processing
Classifier: Development Status :: 4 - Beta
Classifier: Environment :: Console
Classifier: Intended Audience :: Developers
Classifier: License :: OSI Approved :: MIT License
Classifier: Operating System :: OS Independent
Classifier: Programming Language :: Python :: 3
Classifier: Programming Language :: Python :: 3.11
Classifier: Programming Language :: Python :: 3.12
Classifier: Topic :: Scientific/Engineering :: Artificial Intelligence
Classifier: Topic :: Text Processing :: Indexing
Requires-Python: >=3.12
License-File: LICENSE
Requires-Dist: python-dotenv>=1.0.0
Requires-Dist: google-generativeai>=0.7.0
Requires-Dist: langchain-core>=0.3.0
Requires-Dist: langchain-classic>=1.0.0
Requires-Dist: langchain-community>=0.3.0
Requires-Dist: langchain-postgres>=0.0.12
Requires-Dist: langchain-text-splitters>=0.3.0
Requires-Dist: langchain-openai>=0.2.0
Requires-Dist: langchain-google-genai>=2.0.0
Requires-Dist: pymupdf>=1.24.0
Requires-Dist: psycopg[binary,pool]>=3.2.0
Provides-Extra: dev
Requires-Dist: build>=1.0.0; extra == "dev"
Requires-Dist: twine>=4.0.0; extra == "dev"
Requires-Dist: ruff>=0.1.0; extra == "dev"
Requires-Dist: mypy>=1.0.0; extra == "dev"
Provides-Extra: test
Requires-Dist: pytest>=7.0.0; extra == "test"
Requires-Dist: pytest-cov>=4.0.0; extra == "test"
Provides-Extra: docling
Requires-Dist: langchain-docling>=2.0.0; extra == "docling"
Dynamic: license-file
